{
  "diagramType": "stateDiagram",
  "layout": {
    "StateDiagramV2": {
      "nodes": [
        {
          "id": "Crash",
          "x": 306.56,
          "y": 315.0,
          "width": 53.12,
          "height": 40.0,
          "is_cluster": false
        },
        {
          "id": "Moving",
          "x": 337.56,
          "y": 152.5,
          "width": 62.72,
          "height": 201.0,
          "is_cluster": true
        },
        {
          "id": "Still",
          "x": 207.04,
          "y": 315.0,
          "width": 45.92,
          "height": 40.0,
          "is_cluster": false
        },
        {
          "id": "a",
          "x": 11.44,
          "y": 20.0,
          "width": 22.88,
          "height": 40.0,
          "is_cluster": false
        },
        {
          "id": "a_a",
          "x": 90.4,
          "y": 20.0,
          "width": 35.04,
          "height": 40.0,
          "is_cluster": false
        },
        {
          "id": "b",
          "x": 167.72,
          "y": 167.5,
          "width": 22.88,
          "height": 40.0,
          "is_cluster": false
        },
        {
          "id": "b_b",
          "x": 246.68,
          "y": 167.5,
          "width": 35.04,
          "height": 40.0,
          "is_cluster": false
        },
        {
          "id": "fast",
          "x": 337.56,
          "y": 225.0,
          "width": 43.52,
          "height": 40.0,
          "is_cluster": false
        },
        {
          "id": "id1",
          "x": 240.08,
          "y": 20.0,
          "width": 36.32,
          "height": 40.0,
          "is_cluster": false
        },
        {
          "id": "id2",
          "x": 326.4,
          "y": 20.0,
          "width": 36.32,
          "height": 40.0,
          "is_cluster": false
        },
        {
          "id": "id3",
          "x": 412.72,
          "y": 20.0,
          "width": 36.32,
          "height": 40.0,
          "is_cluster": false
        },
        {
          "id": "id4",
          "x": 499.04,
          "y": 20.0,
          "width": 36.32,
          "height": 40.0,
          "is_cluster": false
        },
        {
          "id": "root_start",
          "x": 164.92,
          "y": 20.0,
          "width": 14.0,
          "height": 14.0,
          "is_cluster": false
        },
        {
          "id": "slow",
          "x": 337.56,
          "y": 110.0,
          "width": 46.72,
          "height": 40.0,
          "is_cluster": false
        }
      ],
      "edges": [
        {
          "id": "edge0",
          "from": "a",
          "to": "b",
          "from_cluster": null,
          "to_cluster": null,
          "points": [
            {
              "x": 11.44,
              "y": 40.0
            },
            {
              "x": 89.58,
              "y": 93.75
            },
            {
              "x": 167.72,
              "y": 147.5
            }
          ],
          "label": null,
          "start_label_left": null,
          "start_label_right": null,
          "end_label_left": null,
          "end_label_right": null,
          "start_marker": null,
          "end_marker": null,
          "stroke_dasharray": null
        },
        {
          "id": "edge1",
          "from": "a_a",
          "to": "b_b",
          "from_cluster": null,
          "to_cluster": null,
          "points": [
            {
              "x": 90.4,
              "y": 40.0
            },
            {
              "x": 168.54,
              "y": 93.75
            },
            {
              "x": 246.68,
              "y": 147.5
            }
          ],
          "label": null,
          "start_label_left": null,
          "start_label_right": null,
          "end_label_left": null,
          "end_label_right": null,
          "start_marker": null,
          "end_marker": null,
          "stroke_dasharray": null
        },
        {
          "id": "edge2",
          "from": "a",
          "to": "b",
          "from_cluster": null,
          "to_cluster": null,
          "points": [
            {
              "x": 11.44,
              "y": 40.0
            },
            {
              "x": 89.58,
              "y": 93.75
            },
            {
              "x": 167.72,
              "y": 147.5
            }
          ],
          "label": null,
          "start_label_left": null,
          "start_label_right": null,
          "end_label_left": null,
          "end_label_right": null,
          "start_marker": null,
          "end_marker": null,
          "stroke_dasharray": null
        },
        {
          "id": "edge3",
          "from": "root_start",
          "to": "b",
          "from_cluster": null,
          "to_cluster": null,
          "points": [
            {
              "x": 164.92,
              "y": 27.0
            },
            {
              "x": 166.32,
              "y": 87.25
            },
            {
              "x": 167.72,
              "y": 147.5
            }
          ],
          "label": null,
          "start_label_left": null,
          "start_label_right": null,
          "end_label_left": null,
          "end_label_right": null,
          "start_marker": null,
          "end_marker": null,
          "stroke_dasharray": null
        },
        {
          "id": "edge4",
          "from": "a",
          "to": "b",
          "from_cluster": null,
          "to_cluster": null,
          "points": [
            {
              "x": 11.44,
              "y": 40.0
            },
            {
              "x": 89.58,
              "y": 93.75
            },
            {
              "x": 167.72,
              "y": 147.5
            }
          ],
          "label": null,
          "start_label_left": null,
          "start_label_right": null,
          "end_label_left": null,
          "end_label_right": null,
          "start_marker": null,
          "end_marker": null,
          "stroke_dasharray": null
        },
        {
          "id": "edge5",
          "from": "a",
          "to": "b",
          "from_cluster": null,
          "to_cluster": null,
          "points": [
            {
              "x": 11.44,
              "y": 40.0
            },
            {
              "x": 89.58,
              "y": 93.75
            },
            {
              "x": 167.72,
              "y": 147.5
            }
          ],
          "label": null,
          "start_label_left": null,
          "start_label_right": null,
          "end_label_left": null,
          "end_label_right": null,
          "start_marker": null,
          "end_marker": null,
          "stroke_dasharray": null
        },
        {
          "id": "edge6",
          "from": "root_start",
          "to": "Moving",
          "from_cluster": null,
          "to_cluster": null,
          "points": [
            {
              "x": 164.92,
              "y": 27.0
            },
            {
              "x": 251.24,
              "y": 58.5
            },
            {
              "x": 337.56,
              "y": 90.0
            }
          ],
          "label": null,
          "start_label_left": null,
          "start_label_right": null,
          "end_label_left": null,
          "end_label_right": null,
          "start_marker": null,
          "end_marker": null,
          "stroke_dasharray": null
        },
        {
          "id": "edge7",
          "from": "Moving",
          "to": "Still",
          "from_cluster": null,
          "to_cluster": null,
          "points": [
            {
              "x": 337.56,
              "y": 245.0
            },
            {
              "x": 272.3,
              "y": 270.0
            },
            {
              "x": 207.04,
              "y": 295.0
            }
          ],
          "label": null,
          "start_label_left": null,
          "start_label_right": null,
          "end_label_left": null,
          "end_label_right": null,
          "start_marker": null,
          "end_marker": null,
          "stroke_dasharray": null
        },
        {
          "id": "edge8",
          "from": "Moving",
          "to": "Crash",
          "from_cluster": null,
          "to_cluster": null,
          "points": [
            {
              "x": 337.56,
              "y": 245.0
            },
            {
              "x": 322.06,
              "y": 270.0
            },
            {
              "x": 306.56,
              "y": 295.0
            }
          ],
          "label": null,
          "start_label_left": null,
          "start_label_right": null,
          "end_label_left": null,
          "end_label_right": null,
          "start_marker": null,
          "end_marker": null,
          "stroke_dasharray": null
        },
        {
          "id": "edge9",
          "from": "slow",
          "to": "fast",
          "from_cluster": null,
          "to_cluster": null,
          "points": [
            {
              "x": 337.56,
              "y": 130.0
            },
            {
              "x": 337.56,
              "y": 167.5
            },
            {
              "x": 337.56,
              "y": 205.0
            }
          ],
          "label": null,
          "start_label_left": null,
          "start_label_right": null,
          "end_label_left": null,
          "end_label_right": null,
          "start_marker": null,
          "end_marker": null,
          "stroke_dasharray": null
        }
      ],
      "clusters": [
        {
          "id": "Moving",
          "x": 337.56,
          "y": 152.5,
          "width": 62.72,
          "height": 201.0,
          "diff": -8.0,
          "offset_y": 20.0,
          "title": "Moving",
          "title_label": {
            "x": 337.56,
            "y": 65.0,
            "width": 41.6,
            "height": 24.0
          },
          "requested_dir": "TB",
          "effective_dir": "TB",
          "padding": 8.0,
          "title_margin_top": 0.0,
          "title_margin_bottom": 0.0
        }
      ],
      "bounds": {
        "min_x": 0.0,
        "min_y": 0.0,
        "max_x": 517.2,
        "max_y": 335.0
      }
    }
  }
}
