{
  "diagramType": "stateDiagram",
  "layout": {
    "StateDiagramV2": {
      "nodes": [
        {
          "id": "Active",
          "x": 214.48,
          "y": 134.0,
          "width": 444.96,
          "height": 216.0,
          "is_cluster": true
        },
        {
          "id": "CapsLockOff",
          "x": 209.36,
          "y": 206.0,
          "width": 101.76,
          "height": 40.0,
          "is_cluster": false
        },
        {
          "id": "NumLockOff",
          "x": 58.24,
          "y": 206.0,
          "width": 100.48,
          "height": 40.0,
          "is_cluster": false
        },
        {
          "id": "ScrollLockOff",
          "x": 365.6,
          "y": 206.0,
          "width": 110.72,
          "height": 40.0,
          "is_cluster": false
        },
        {
          "id": "divider-id-1",
          "x": 58.24,
          "y": 149.0,
          "width": 116.48,
          "height": 170.0,
          "is_cluster": true
        },
        {
          "id": "divider-id-1_start",
          "x": 58.24,
          "y": 79.0,
          "width": 14.0,
          "height": 14.0,
          "is_cluster": false
        },
        {
          "id": "divider-id-2",
          "x": 209.36,
          "y": 149.0,
          "width": 117.76,
          "height": 170.0,
          "is_cluster": true
        },
        {
          "id": "divider-id-2_start",
          "x": 209.36,
          "y": 79.0,
          "width": 14.0,
          "height": 14.0,
          "is_cluster": false
        },
        {
          "id": "id-38dvt516gkfs-1",
          "x": 365.6,
          "y": 149.0,
          "width": 126.72,
          "height": 170.0,
          "is_cluster": true
        },
        {
          "id": "id-38dvt516gkfs-1_start",
          "x": 365.6,
          "y": 79.0,
          "width": 14.0,
          "height": 14.0,
          "is_cluster": false
        },
        {
          "id": "root_start",
          "x": 214.48,
          "y": 15.0,
          "width": 14.0,
          "height": 14.0,
          "is_cluster": false
        }
      ],
      "edges": [
        {
          "id": "edge0",
          "from": "root_start",
          "to": "Active",
          "from_cluster": null,
          "to_cluster": null,
          "points": [
            {
              "x": 214.48,
              "y": 22.0
            },
            {
              "x": 214.48,
              "y": 47.0
            },
            {
              "x": 214.48,
              "y": 134.0
            }
          ],
          "label": null,
          "start_label_left": null,
          "start_label_right": null,
          "end_label_left": null,
          "end_label_right": null,
          "start_marker": null,
          "end_marker": null,
          "stroke_dasharray": null
        },
        {
          "id": "edge1",
          "from": "divider-id-1_start",
          "to": "NumLockOff",
          "from_cluster": null,
          "to_cluster": null,
          "points": [
            {
              "x": 58.24,
              "y": 86.0
            },
            {
              "x": 58.24,
              "y": 136.0
            },
            {
              "x": 58.74,
              "y": 186.5
            }
          ],
          "label": null,
          "start_label_left": null,
          "start_label_right": null,
          "end_label_left": null,
          "end_label_right": null,
          "start_marker": null,
          "end_marker": null,
          "stroke_dasharray": null
        },
        {
          "id": "edge2",
          "from": "divider-id-2_start",
          "to": "CapsLockOff",
          "from_cluster": null,
          "to_cluster": null,
          "points": [
            {
              "x": 209.36,
              "y": 86.0
            },
            {
              "x": 209.36,
              "y": 136.0
            },
            {
              "x": 209.86,
              "y": 186.5
            }
          ],
          "label": null,
          "start_label_left": null,
          "start_label_right": null,
          "end_label_left": null,
          "end_label_right": null,
          "start_marker": null,
          "end_marker": null,
          "stroke_dasharray": null
        },
        {
          "id": "edge3",
          "from": "id-38dvt516gkfs-1_start",
          "to": "ScrollLockOff",
          "from_cluster": null,
          "to_cluster": null,
          "points": [
            {
              "x": 365.6,
              "y": 86.0
            },
            {
              "x": 365.6,
              "y": 136.0
            },
            {
              "x": 366.1,
              "y": 186.5
            }
          ],
          "label": null,
          "start_label_left": null,
          "start_label_right": null,
          "end_label_left": null,
          "end_label_right": null,
          "start_marker": null,
          "end_marker": null,
          "stroke_dasharray": null
        }
      ],
      "clusters": [
        {
          "id": "Active",
          "x": 214.48,
          "y": 134.0,
          "width": 444.96,
          "height": 216.0,
          "diff": -8.0,
          "offset_y": 20.0,
          "title": "Active",
          "title_label": {
            "x": 214.48,
            "y": 39.0,
            "width": 41.6,
            "height": 24.0
          },
          "requested_dir": "TB",
          "effective_dir": "TB",
          "padding": 8.0,
          "title_margin_top": 0.0,
          "title_margin_bottom": 0.0
        },
        {
          "id": "divider-id-1",
          "x": 58.24,
          "y": 149.0,
          "width": 116.48,
          "height": 170.0,
          "diff": -8.0,
          "offset_y": 0.0,
          "title": "",
          "title_label": {
            "x": 58.24,
            "y": 65.0,
            "width": 0.0,
            "height": 0.0
          },
          "requested_dir": "TB",
          "effective_dir": "TB",
          "padding": 8.0,
          "title_margin_top": 0.0,
          "title_margin_bottom": 0.0
        },
        {
          "id": "divider-id-2",
          "x": 209.36,
          "y": 149.0,
          "width": 117.76,
          "height": 170.0,
          "diff": -8.0,
          "offset_y": 0.0,
          "title": "",
          "title_label": {
            "x": 209.36,
            "y": 65.0,
            "width": 0.0,
            "height": 0.0
          },
          "requested_dir": "TB",
          "effective_dir": "TB",
          "padding": 8.0,
          "title_margin_top": 0.0,
          "title_margin_bottom": 0.0
        },
        {
          "id": "id-38dvt516gkfs-1",
          "x": 365.6,
          "y": 149.0,
          "width": 126.72,
          "height": 170.0,
          "diff": -8.0,
          "offset_y": 0.0,
          "title": "",
          "title_label": {
            "x": 365.6,
            "y": 65.0,
            "width": 0.0,
            "height": 0.0
          },
          "requested_dir": "TB",
          "effective_dir": "TB",
          "padding": 8.0,
          "title_margin_top": 0.0,
          "title_margin_bottom": 0.0
        }
      ],
      "bounds": {
        "min_x": -8.0,
        "min_y": 8.0,
        "max_x": 436.96,
        "max_y": 242.0
      }
    }
  }
}
