{
  "diagramType": "sequence",
  "layout": {
    "SequenceDiagram": {
      "nodes": [
        {
          "id": "actor-top-U",
          "x": 75.0,
          "y": 32.5,
          "width": 150.0,
          "height": 65.0,
          "is_cluster": false
        },
        {
          "id": "actor-top-WEB",
          "x": 275.0,
          "y": 32.5,
          "width": 150.0,
          "height": 65.0,
          "is_cluster": false
        },
        {
          "id": "actor-top-API",
          "x": 475.0,
          "y": 42.0,
          "width": 150.0,
          "height": 84.0,
          "is_cluster": false
        },
        {
          "id": "actor-top-AUTH",
          "x": 675.0,
          "y": 32.0,
          "width": 150.0,
          "height": 64.0,
          "is_cluster": false
        },
        {
          "id": "actor-top-Q",
          "x": 875.0,
          "y": 32.5,
          "width": 150.0,
          "height": 65.0,
          "is_cluster": false
        },
        {
          "id": "actor-top-W",
          "x": 1075.0,
          "y": 32.0,
          "width": 150.0,
          "height": 64.0,
          "is_cluster": false
        },
        {
          "id": "actor-top-DB",
          "x": 1275.0,
          "y": 35.0,
          "width": 150.0,
          "height": 70.0,
          "is_cluster": false
        },
        {
          "id": "actor-top-LOG",
          "x": 1475.0,
          "y": 32.5,
          "width": 150.0,
          "height": 65.0,
          "is_cluster": false
        },
        {
          "id": "actor-bottom-U",
          "x": 75.0,
          "y": 659.9,
          "width": 150.0,
          "height": 65.0,
          "is_cluster": false
        },
        {
          "id": "actor-bottom-WEB",
          "x": 275.0,
          "y": 659.9,
          "width": 150.0,
          "height": 65.0,
          "is_cluster": false
        },
        {
          "id": "actor-bottom-API",
          "x": 475.0,
          "y": 669.4,
          "width": 150.0,
          "height": 84.0,
          "is_cluster": false
        },
        {
          "id": "actor-bottom-AUTH",
          "x": 675.0,
          "y": 659.4,
          "width": 150.0,
          "height": 64.0,
          "is_cluster": false
        },
        {
          "id": "actor-bottom-Q",
          "x": 875.0,
          "y": 659.9,
          "width": 150.0,
          "height": 65.0,
          "is_cluster": false
        },
        {
          "id": "actor-bottom-W",
          "x": 1075.0,
          "y": 659.4,
          "width": 150.0,
          "height": 64.0,
          "is_cluster": false
        },
        {
          "id": "actor-bottom-DB",
          "x": 1275.0,
          "y": 662.4,
          "width": 150.0,
          "height": 70.0,
          "is_cluster": false
        },
        {
          "id": "actor-bottom-LOG",
          "x": 1475.0,
          "y": 659.9,
          "width": 150.0,
          "height": 65.0,
          "is_cluster": false
        }
      ],
      "edges": [
        {
          "id": "msg-0",
          "from": "U",
          "to": "WEB",
          "from_cluster": null,
          "to_cluster": null,
          "points": [
            {
              "x": 76.0,
              "y": 110.2
            },
            {
              "x": 271.0,
              "y": 110.2
            }
          ],
          "label": {
            "x": 174.0,
            "y": 80.0,
            "width": 28.0,
            "height": 17.6
          },
          "start_label_left": null,
          "start_label_right": null,
          "end_label_left": null,
          "end_label_right": null,
          "start_marker": null,
          "end_marker": null,
          "stroke_dasharray": null
        },
        {
          "id": "msg-1",
          "from": "WEB",
          "to": "API",
          "from_cluster": null,
          "to_cluster": null,
          "points": [
            {
              "x": 276.0,
              "y": 155.4
            },
            {
              "x": 471.0,
              "y": 155.4
            }
          ],
          "label": {
            "x": 374.0,
            "y": 125.0,
            "width": 48.0,
            "height": 17.6
          },
          "start_label_left": null,
          "start_label_right": null,
          "end_label_left": null,
          "end_label_right": null,
          "start_marker": null,
          "end_marker": null,
          "stroke_dasharray": null
        },
        {
          "id": "msg-2",
          "from": "API",
          "to": "AUTH",
          "from_cluster": null,
          "to_cluster": null,
          "points": [
            {
              "x": 476.0,
              "y": 200.6
            },
            {
              "x": 671.0,
              "y": 200.6
            }
          ],
          "label": {
            "x": 574.0,
            "y": 170.0,
            "width": 41.0,
            "height": 17.6
          },
          "start_label_left": null,
          "start_label_right": null,
          "end_label_left": null,
          "end_label_right": null,
          "start_marker": null,
          "end_marker": null,
          "stroke_dasharray": null
        },
        {
          "id": "msg-3",
          "from": "AUTH",
          "to": "API",
          "from_cluster": null,
          "to_cluster": null,
          "points": [
            {
              "x": 674.0,
              "y": 245.8
            },
            {
              "x": 479.0,
              "y": 245.8
            }
          ],
          "label": {
            "x": 577.0,
            "y": 216.0,
            "width": 16.0,
            "height": 17.6
          },
          "start_label_left": null,
          "start_label_right": null,
          "end_label_left": null,
          "end_label_right": null,
          "start_marker": null,
          "end_marker": null,
          "stroke_dasharray": null
        },
        {
          "id": "msg-4",
          "from": "API",
          "to": "Q",
          "from_cluster": null,
          "to_cluster": null,
          "points": [
            {
              "x": 476.0,
              "y": 291.0
            },
            {
              "x": 871.0,
              "y": 291.0
            }
          ],
          "label": {
            "x": 674.0,
            "y": 261.0,
            "width": 48.0,
            "height": 17.6
          },
          "start_label_left": null,
          "start_label_right": null,
          "end_label_left": null,
          "end_label_right": null,
          "start_marker": null,
          "end_marker": null,
          "stroke_dasharray": null
        },
        {
          "id": "msg-5",
          "from": "Q",
          "to": "W",
          "from_cluster": null,
          "to_cluster": null,
          "points": [
            {
              "x": 876.0,
              "y": 336.2
            },
            {
              "x": 1071.0,
              "y": 336.2
            }
          ],
          "label": {
            "x": 974.0,
            "y": 306.0,
            "width": 43.0,
            "height": 17.6
          },
          "start_label_left": null,
          "start_label_right": null,
          "end_label_left": null,
          "end_label_right": null,
          "start_marker": null,
          "end_marker": null,
          "stroke_dasharray": null
        },
        {
          "id": "msg-6",
          "from": "W",
          "to": "DB",
          "from_cluster": null,
          "to_cluster": null,
          "points": [
            {
              "x": 1076.0,
              "y": 381.4
            },
            {
              "x": 1271.0,
              "y": 381.4
            }
          ],
          "label": {
            "x": 1174.0,
            "y": 351.0,
            "width": 38.0,
            "height": 17.6
          },
          "start_label_left": null,
          "start_label_right": null,
          "end_label_left": null,
          "end_label_right": null,
          "start_marker": null,
          "end_marker": null,
          "stroke_dasharray": null
        },
        {
          "id": "msg-7",
          "from": "DB",
          "to": "W",
          "from_cluster": null,
          "to_cluster": null,
          "points": [
            {
              "x": 1274.0,
              "y": 426.6
            },
            {
              "x": 1079.0,
              "y": 426.6
            }
          ],
          "label": {
            "x": 1177.0,
            "y": 396.0,
            "width": 16.0,
            "height": 17.6
          },
          "start_label_left": null,
          "start_label_right": null,
          "end_label_left": null,
          "end_label_right": null,
          "start_marker": null,
          "end_marker": null,
          "stroke_dasharray": null
        },
        {
          "id": "msg-8",
          "from": "W",
          "to": "LOG",
          "from_cluster": null,
          "to_cluster": null,
          "points": [
            {
              "x": 1076.0,
              "y": 471.8
            },
            {
              "x": 1471.0,
              "y": 471.8
            }
          ],
          "label": {
            "x": 1274.0,
            "y": 442.0,
            "width": 41.0,
            "height": 17.6
          },
          "start_label_left": null,
          "start_label_right": null,
          "end_label_left": null,
          "end_label_right": null,
          "start_marker": null,
          "end_marker": null,
          "stroke_dasharray": null
        },
        {
          "id": "msg-9",
          "from": "LOG",
          "to": "W",
          "from_cluster": null,
          "to_cluster": null,
          "points": [
            {
              "x": 1474.0,
              "y": 517.0
            },
            {
              "x": 1079.0,
              "y": 517.0
            }
          ],
          "label": {
            "x": 1277.0,
            "y": 487.0,
            "width": 16.0,
            "height": 17.6
          },
          "start_label_left": null,
          "start_label_right": null,
          "end_label_left": null,
          "end_label_right": null,
          "start_marker": null,
          "end_marker": null,
          "stroke_dasharray": null
        },
        {
          "id": "msg-10",
          "from": "API",
          "to": "WEB",
          "from_cluster": null,
          "to_cluster": null,
          "points": [
            {
              "x": 474.0,
              "y": 562.2
            },
            {
              "x": 279.0,
              "y": 562.2
            }
          ],
          "label": {
            "x": 377.0,
            "y": 532.0,
            "width": 27.0,
            "height": 17.6
          },
          "start_label_left": null,
          "start_label_right": null,
          "end_label_left": null,
          "end_label_right": null,
          "start_marker": null,
          "end_marker": null,
          "stroke_dasharray": null
        },
        {
          "id": "msg-11",
          "from": "WEB",
          "to": "U",
          "from_cluster": null,
          "to_cluster": null,
          "points": [
            {
              "x": 274.0,
              "y": 607.4
            },
            {
              "x": 79.0,
              "y": 607.4
            }
          ],
          "label": {
            "x": 177.0,
            "y": 577.0,
            "width": 28.0,
            "height": 17.6
          },
          "start_label_left": null,
          "start_label_right": null,
          "end_label_left": null,
          "end_label_right": null,
          "start_marker": null,
          "end_marker": null,
          "stroke_dasharray": null
        },
        {
          "id": "lifeline-U",
          "from": "actor-top-U",
          "to": "actor-bottom-U",
          "from_cluster": null,
          "to_cluster": null,
          "points": [
            {
              "x": 75.0,
              "y": 65.0
            },
            {
              "x": 75.0,
              "y": 627.4
            }
          ],
          "label": null,
          "start_label_left": null,
          "start_label_right": null,
          "end_label_left": null,
          "end_label_right": null,
          "start_marker": null,
          "end_marker": null,
          "stroke_dasharray": null
        },
        {
          "id": "lifeline-WEB",
          "from": "actor-top-WEB",
          "to": "actor-bottom-WEB",
          "from_cluster": null,
          "to_cluster": null,
          "points": [
            {
              "x": 275.0,
              "y": 65.0
            },
            {
              "x": 275.0,
              "y": 627.4
            }
          ],
          "label": null,
          "start_label_left": null,
          "start_label_right": null,
          "end_label_left": null,
          "end_label_right": null,
          "start_marker": null,
          "end_marker": null,
          "stroke_dasharray": null
        },
        {
          "id": "lifeline-API",
          "from": "actor-top-API",
          "to": "actor-bottom-API",
          "from_cluster": null,
          "to_cluster": null,
          "points": [
            {
              "x": 475.0,
              "y": 75.0
            },
            {
              "x": 475.0,
              "y": 627.4
            }
          ],
          "label": null,
          "start_label_left": null,
          "start_label_right": null,
          "end_label_left": null,
          "end_label_right": null,
          "start_marker": null,
          "end_marker": null,
          "stroke_dasharray": null
        },
        {
          "id": "lifeline-AUTH",
          "from": "actor-top-AUTH",
          "to": "actor-bottom-AUTH",
          "from_cluster": null,
          "to_cluster": null,
          "points": [
            {
              "x": 675.0,
              "y": 75.0
            },
            {
              "x": 675.0,
              "y": 627.4
            }
          ],
          "label": null,
          "start_label_left": null,
          "start_label_right": null,
          "end_label_left": null,
          "end_label_right": null,
          "start_marker": null,
          "end_marker": null,
          "stroke_dasharray": null
        },
        {
          "id": "lifeline-Q",
          "from": "actor-top-Q",
          "to": "actor-bottom-Q",
          "from_cluster": null,
          "to_cluster": null,
          "points": [
            {
              "x": 875.0,
              "y": 65.0
            },
            {
              "x": 875.0,
              "y": 627.4
            }
          ],
          "label": null,
          "start_label_left": null,
          "start_label_right": null,
          "end_label_left": null,
          "end_label_right": null,
          "start_marker": null,
          "end_marker": null,
          "stroke_dasharray": null
        },
        {
          "id": "lifeline-W",
          "from": "actor-top-W",
          "to": "actor-bottom-W",
          "from_cluster": null,
          "to_cluster": null,
          "points": [
            {
              "x": 1075.0,
              "y": 80.0
            },
            {
              "x": 1075.0,
              "y": 627.4
            }
          ],
          "label": null,
          "start_label_left": null,
          "start_label_right": null,
          "end_label_left": null,
          "end_label_right": null,
          "start_marker": null,
          "end_marker": null,
          "stroke_dasharray": null
        },
        {
          "id": "lifeline-DB",
          "from": "actor-top-DB",
          "to": "actor-bottom-DB",
          "from_cluster": null,
          "to_cluster": null,
          "points": [
            {
              "x": 1275.0,
              "y": 75.0
            },
            {
              "x": 1275.0,
              "y": 627.4
            }
          ],
          "label": null,
          "start_label_left": null,
          "start_label_right": null,
          "end_label_left": null,
          "end_label_right": null,
          "start_marker": null,
          "end_marker": null,
          "stroke_dasharray": null
        },
        {
          "id": "lifeline-LOG",
          "from": "actor-top-LOG",
          "to": "actor-bottom-LOG",
          "from_cluster": null,
          "to_cluster": null,
          "points": [
            {
              "x": 1475.0,
              "y": 65.0
            },
            {
              "x": 1475.0,
              "y": 627.4
            }
          ],
          "label": null,
          "start_label_left": null,
          "start_label_right": null,
          "end_label_left": null,
          "end_label_right": null,
          "start_marker": null,
          "end_marker": null,
          "stroke_dasharray": null
        }
      ],
      "clusters": [],
      "bounds": {
        "min_x": -50.0,
        "min_y": -10.0,
        "max_x": 1600.0,
        "max_y": 722.4
      }
    }
  }
}
